pymetallic/__init__.py
pymetallic/helpers.py
pymetallic/libpymetallic.dylib
pymetallic/metallic.py
pymetallic/kernels/#__init__.py#
pymetallic/kernels/README.md
pymetallic/kernels/__init__.py
pymetallic/kernels/demo_kernels.metal
pymetallic/kernels/fluid_simulation.metal
pymetallic/kernels/game_of_life.metal
pymetallic/kernels/helper_kernels.metal
pymetallic/kernels/image_processing.metal
pymetallic/kernels/linalg_kernels.metal
pymetallic/scripts/__init__.py
pymetallic/scripts/demo.py
pymetallic/scripts/smoke.py
pymetallic-0.3.1.dist-info/METADATA
pymetallic-0.3.1.dist-info/WHEEL
pymetallic-0.3.1.dist-info/entry_points.txt
pymetallic-0.3.1.dist-info/licenses/LICENSE
pymetallic-0.3.1.dist-info/RECORD
