Metadata-Version: 2.4
Name: pymetallic
Version: 0.3.1
Summary: Python bindings for Apple Metal using swift-cffi
Project-URL: Homepage, https://github.com/seantrue/pymetallic
Project-URL: Documentation, https://pymetallic.readthedocs.io/
Project-URL: Repository, https://github.com/seantrue/pymetallic.git
Project-URL: Bug Tracker, https://github.com/seantrue/pymetallic/issues
Author: Sean D. True
License: MIT
License-File: LICENSE
Keywords: apple,compute,gpu,macos,metal,opencl
Classifier: Development Status :: 4 - Beta
Classifier: Intended Audience :: Developers
Classifier: License :: OSI Approved :: MIT License
Classifier: Operating System :: MacOS :: MacOS X
Classifier: Programming Language :: Python :: 3
Classifier: Programming Language :: Python :: 3.10
Classifier: Programming Language :: Python :: 3.11
Classifier: Programming Language :: Python :: 3.12
Classifier: Programming Language :: Python :: 3.13
Classifier: Topic :: Scientific/Engineering
Classifier: Topic :: Software Development :: Libraries :: Python Modules
Requires-Python: >=3.10
Requires-Dist: numpy>=2.1
Provides-Extra: dev
Requires-Dist: black>=22.0; extra == 'dev'
Requires-Dist: build>=0.8; extra == 'dev'
Requires-Dist: isort>=5.0; extra == 'dev'
Requires-Dist: licensecheck>=2025.1.0; extra == 'dev'
Requires-Dist: mypy>=0.950; extra == 'dev'
Requires-Dist: pillow>=11.3.0; extra == 'dev'
Requires-Dist: pytest-benchmark>=3.4; extra == 'dev'
Requires-Dist: pytest-cov>=3.0; extra == 'dev'
Requires-Dist: pytest>=6.0; extra == 'dev'
Requires-Dist: ruff>=0.1.0; extra == 'dev'
Requires-Dist: twine>=4.0; extra == 'dev'
Requires-Dist: wheel>=0.37; extra == 'dev'
Provides-Extra: docs
Requires-Dist: myst-parser>=0.18; extra == 'docs'
Requires-Dist: sphinx-rtd-theme>=1.0; extra == 'docs'
Requires-Dist: sphinx>=4.0; extra == 'docs'
Provides-Extra: test
Requires-Dist: pillow>=11.3.0; extra == 'test'
Requires-Dist: pytest-benchmark>=3.4; extra == 'test'
Requires-Dist: pytest-cov>=3.0; extra == 'test'
Requires-Dist: pytest>=6.0; extra == 'test'
